transifex_client-0.12.5.dist-info/DESCRIPTION.rst
transifex_client-0.12.5.dist-info/METADATA
transifex_client-0.12.5.dist-info/RECORD
transifex_client-0.12.5.dist-info/WHEEL
transifex_client-0.12.5.dist-info/entry_points.txt
transifex_client-0.12.5.dist-info/metadata.json
transifex_client-0.12.5.dist-info/top_level.txt
txclib/__init__.py
txclib/__main__.py
txclib/cacert.pem
txclib/cmdline.py
txclib/commands.py
txclib/config.py
txclib/exceptions.py
txclib/log.py
txclib/parsers.py
txclib/paths.py
txclib/processors.py
txclib/project.py
txclib/urls.py
txclib/utils.py
txclib/web.py
