Metadata-Version: 2.0
Name: transifex-client
Version: 0.12.5
Summary: A command line interface for Transifex
Home-page: https://www.transifex.com
Author: Transifex
Author-email: admin@transifex.com
License: GPLv2
Keywords: translation,localization,internationalization
Platform: UNKNOWN
Classifier: Programming Language :: Python
Classifier: Programming Language :: Python :: 2
Classifier: Programming Language :: Python :: 2.6
Classifier: Programming Language :: Python :: 2.7
Classifier: Programming Language :: Python :: 3.3
Classifier: Programming Language :: Python :: 3.5
Requires-Dist: urllib3
Requires-Dist: six
